mdpsolver/__init__.py
mdpsolver/model.py
mdpsolver/solvermodule.cp310-win_amd64.pyd
mdpsolver/solvermodule.cp311-win_amd64.pyd
mdpsolver/solvermodule.cp312-win_amd64.pyd
mdpsolver/solvermodule.cp313-win_amd64.pyd
mdpsolver/solvermodule.cpython-310-x86_64-linux-gnu.so
mdpsolver/solvermodule.cpython-311-x86_64-linux-gnu.so
mdpsolver/solvermodule.cpython-312-x86_64-linux-gnu.so
mdpsolver/solvermodule.cpython-313-x86_64-linux-gnu.so
mdpsolver/problems/cbmaux.py
mdpsolver/problems/tbmaux.py
mdpsolver/problems/__pycache__/cbmaux.cpython-310.pyc
mdpsolver/problems/__pycache__/tbmaux.cpython-310.pyc
mdpsolver-0.9.9.dist-info/licenses/LICENSE
mdpsolver-0.9.9.dist-info/METADATA
mdpsolver-0.9.9.dist-info/WHEEL
mdpsolver-0.9.9.dist-info/top_level.txt
mdpsolver-0.9.9.dist-info/RECORD
