Metadata-Version: 2.4
Name: mdpsolver
Version: 0.9.9
Summary: A fast solver for Markov Decision Processes
Author-email: Anders Reenberg Andersen <andersra@live.dk>, Jesper Fink Andersen <jesperfinkandersen@gmail.com>
Project-URL: Homepage, https://github.com/areenberg/MDPSolver
Project-URL: Issues, https://github.com/areenberg/MDPSolver/issues
Classifier: Development Status :: 3 - Alpha
Classifier: Programming Language :: Python :: 3
Classifier: License :: OSI Approved :: MIT License
Classifier: Operating System :: Microsoft :: Windows
Classifier: Operating System :: POSIX :: Linux
Requires-Python: >=3.10
License-File: LICENSE
Dynamic: license-file
